splender/__init__.py
splender/image.py
splender/knot_init.py
splender/optim.py
splender/splender.py
splender/utils.py
splender/video.py
splender-0.1.0.dist-info/METADATA
splender-0.1.0.dist-info/WHEEL
splender-0.1.0.dist-info/top_level.txt
splender-0.1.0.dist-info/RECORD
