Metadata-Version: 2.4
Name: splender
Version: 0.1.0
Summary: Fit splines to images and videos through differentiable rendering.
Author-email: Frans Zdyb <frzd@di.ku.dk>
Project-URL: Homepage, https://github.com/kirkegaardlab/splender
Project-URL: Documentation, https://github.com/kirkegaardlab/splender
Project-URL: Source, https://github.com/kirkegaardlab/splender
Project-URL: Bug Tracker, https://github.com/kirkegaardlab/splender/issues
Keywords: jax,differentiable-rendering,centerline,spline,machine-learning
Classifier: Development Status :: 3 - Alpha
Classifier: Intended Audience :: Developers
Classifier: License :: OSI Approved :: MIT License
Classifier: Programming Language :: Python :: 3
Requires-Dist: jax
Requires-Dist: rustworkx
Requires-Dist: scikit-image
Requires-Dist: interpax
Requires-Dist: matplotlib
Requires-Dist: optax
